mfac/__init__.py
mfac/mfac.py
mfac/controllers/__init__.py
mfac/controllers/cfdl.py
mfac/controllers/ffdl.py
mfac/controllers/pfdl.py
mfac-0.1.17.dist-info/LICENSE
mfac-0.1.17.dist-info/METADATA
mfac-0.1.17.dist-info/WHEEL
mfac-0.1.17.dist-info/top_level.txt
mfac-0.1.17.dist-info/RECORD
