Metadata-Version: 2.1
Name: mfac
Version: 0.1.17
Summary: Model Free Adaptive Control Toolbox
Home-page: https://github.com/shahind/MFAC
Author: Shahin Darvishpoor
Author-email: Shahindarvishpoor@gmail.com
Project-URL: Bug Tracker, https://github.com/shahind/MFAC/issues
Classifier: Programming Language :: Python :: 3
Classifier: License :: OSI Approved :: MIT License
Classifier: Operating System :: OS Independent
Requires-Python: >=3.6
License-File: LICENSE
